{
  "itineraries": [
    {
      "id": 1,
      "parkId": "6DA17C86-088E-4B4D-B862-7C1BD5CF236B"
    },
    {
      "parkId": "1A47416F-DAA3-4137-9F30-14AF86B4E547",
      "id": 2
    },
    {
      "parkId": "E6E1D22A-7A89-47F8-813C-B611059A8CF9",
      "id": 3
    }
  ],
  "itineraryEatery": [
    {
      "id": 1,
      "itineraryId": 1,
      "eateryId": 8
    },
    {
      "id": 1,
      "itineraryId": 1,
      "eateryId": 2
    },
    {
      "EateryId": 32,
      "id": 2
    },
    {
      "EateryId": 22,
      "id": 3
    }
  ],
  "itineraryAttraction": [
    {
      "id": 1,
      "itineraryId": 1,
      "attractionId": 2
    },
    {
      "id": 2,
      "itineraryId": 1,
      "attractionId": 13
    },
    {
      "attractionId": 8,
      "id": 3
    },
    {
      "attractionId": 17,
      "id": 4
    }
  ]
}